DESCRIPTION
LICENSE
MANIFEST.in
README.txt
setup.cfg
setup.py
LinOTP.egg-info/PKG-INFO
LinOTP.egg-info/SOURCES.txt
LinOTP.egg-info/dependency_links.txt
LinOTP.egg-info/entry_points.txt
LinOTP.egg-info/not-zip-safe
LinOTP.egg-info/paster_plugins.txt
LinOTP.egg-info/requires.txt
LinOTP.egg-info/top_level.txt
config/apache-docker.conf.tmpl
config/dictionary
config/dummy-encKey
config/keyidentity-push-ca-bundle.crt
config/linotp-docker.ini.tmpl
config/linotp.ini.example
config/linotp.ini.paster
config/linotp2-ldap.auth
config/linotp2-paster
config/linotp2.pth
config/linotpapp.wsgi
config/who.ini
config/apache2.2-example/linotp2
config/apache2.2-example/linotp2-certs
config/apache2.2-example/linotp2-ldap
config/apache2.2-example/linotp2-radius
config/apache2.4-example/linotp2.conf
examples/mailtemplate-authenticate.eml
examples/mailtemplate-enroll.eml
examples/mailtemplate-set-pin.eml
linotp/__init__.py
linotp/websetup.py
linotp/config/__init__.py
linotp/config/deployment.ini_tmpl
linotp/config/environment.py
linotp/config/middleware.py
linotp/config/routing.py
linotp/controllers/__init__.py
linotp/controllers/admin.py
linotp/controllers/audit.py
linotp/controllers/auth.py
linotp/controllers/error.py
linotp/controllers/gettoken.py
linotp/controllers/helpdesk.py
linotp/controllers/maintenance.py
linotp/controllers/manage.py
linotp/controllers/migrate.py
linotp/controllers/monitoring.py
linotp/controllers/ocra.py
linotp/controllers/openid.py
linotp/controllers/reporting.py
linotp/controllers/selfservice.py
linotp/controllers/system.py
linotp/controllers/tools.py
linotp/controllers/u2f.py
linotp/controllers/userservice.py
linotp/controllers/validate.py
linotp/i18n/de.po
linotp/i18n/de/LC_MESSAGES/linotp.po
linotp/i18n/es/LC_MESSAGES/linotp.po
linotp/i18n/fr/LC_MESSAGES/linotp.po
linotp/i18n/it/LC_MESSAGES/linotp.po
linotp/i18n/zh/LC_MESSAGES/linotp.po
linotp/lib/HMAC.py
linotp/lib/__init__.py
linotp/lib/_compat.py
linotp/lib/app_globals.py
linotp/lib/apps.py
linotp/lib/base.py
linotp/lib/challenges.py
linotp/lib/context.py
linotp/lib/error.py
linotp/lib/helpers.py
linotp/lib/local.py
linotp/lib/log.py
linotp/lib/logs.py
linotp/lib/migrate.py
linotp/lib/module_loader.py
linotp/lib/monitoring.py
linotp/lib/openid.py
