Metadata-Version: 1.1
Name: LinOTP
Version: 2.11.1
Summary: LinOTP Service
Home-page: https://www.linotp.org
Author: KeyIdentity GmbH
Author-email: linotp@keyidentity.com
License: AGPL v3, (C) KeyIdentity GmbH
Platform: UNKNOWN
Classifier: Framework :: Pylons
Classifier: License :: OSI Approved :: GNU Affero General Public License v3
Classifier: Programming Language :: Python
Classifier: Topic :: Internet
Classifier: Topic :: Security
Classifier: Topic :: System :: Systems Administration :: Authentication/Directory
